plada/__init__.py
plada/analyzer.py
plada/core.py
plada/logger.py
plada/main.py
plada/market.py
plada/runner.py
plada/simulator.py
plada/test.py
plada/agents/__init__.py
plada/agents/agent.py
plada/agents/agent_generator.py
plada/agents/agent_network.py
plada/agents/buyer.py
plada/agents/buyer_generator.py
plada/agents/buyer_v2.py
plada/agents/seller.py
plada/agents/seller_generator.py
plada/agents/evaluators/__init__.py
plada/agents/evaluators/data_evaluator.py
plada/agents/evaluators/utility_evaluator.py
plada/agents/strategies/__init__.py
plada/agents/strategies/base_strategy.py
plada/agents/strategies/random_strategy.py
plada/agents/strategies/ranking_strategy.py
plada/agents/strategies/related_strategy.py
plada/analysis/__init__.py
plada/analysis/analyzer.py
plada/datasets/__init__.py
plada/datasets/data.py
plada/datasets/data_generator.py
plada/datasets/data_manager.py
plada/datasets/data_network.py
plada/simulation/__init__.py
plada/simulation/simulator.py
plada/transaction/__init__.py
plada/transaction/transaction.py
plada/variables/__init__.py
plada/variables/variable.py
plada/variables/variable_generator.py
plada/variables/variable_manager.py
plada/variables/variable_network.py
plada-0.0.13.dist-info/METADATA
plada-0.0.13.dist-info/WHEEL
plada-0.0.13.dist-info/top_level.txt
plada-0.0.13.dist-info/RECORD
