Metadata-Version: 2.1
Name: plada
Version: 0.0.13
Summary: PlaDa: Platform for Data market
Author: Jun Sashihara
